brain_games/__init__.py
brain_games/cli.py
brain_games/flow.py
brain_games/games/even.py
brain_games/scripts/__init__.py
brain_games/scripts/brain_even.py
brain_games/scripts/brain_games.py
hexlet_code_nick-0.1.0.dist-info/entry_points.txt
hexlet_code_nick-0.1.0.dist-info/WHEEL
hexlet_code_nick-0.1.0.dist-info/METADATA
hexlet_code_nick-0.1.0.dist-info/RECORD
