Metadata-Version: 2.1
Name: hexlet-code-nick
Version: 0.1.0
Summary: 
Author: Nikita
Author-email: Nick026rus@gmail.com
Requires-Python: >=3.8,<4.0
Classifier: Programming Language :: Python :: 3
Classifier: Programming Language :: Python :: 3.8
Classifier: Programming Language :: Python :: 3.9
Requires-Dist: prompt (>=0.4.1,<0.5.0)
